zerotrust/__init__.py
zerotrust/client.py
zerotrust-0.1.1.dist-info/METADATA
zerotrust-0.1.1.dist-info/WHEEL
zerotrust-0.1.1.dist-info/top_level.txt
zerotrust-0.1.1.dist-info/RECORD
