Metadata-Version: 2.1
Name: zerotrust
Version: 0.1.1
Summary: A Python package for interacting with FastAPI endpoints
Author: sohaib anwar
Author-email: sohaibanwaar1203@gmail.com
Requires-Dist: fastapi
Requires-Dist: requests
